odoo/addons/oca_custom/README.rst
odoo/addons/oca_custom/__init__.py
odoo/addons/oca_custom/__manifest__.py
odoo/addons/oca_custom/models/__init__.py
odoo/addons/oca_custom/models/res_partner.py
odoo/addons/oca_custom/readme/CONTRIBUTORS.rst
odoo/addons/oca_custom/readme/DESCRIPTION.rst
odoo/addons/oca_custom/readme/ROADMAP.rst
odoo/addons/oca_custom/static/description/icon.png
odoo/addons/oca_custom/static/description/index.html
odoo/addons/oca_custom/views/res_partner.xml
odoo12_addon_oca_custom-12.0.1.0.0.99.dev3.dist-info/METADATA
odoo12_addon_oca_custom-12.0.1.0.0.99.dev3.dist-info/WHEEL
odoo12_addon_oca_custom-12.0.1.0.0.99.dev3.dist-info/top_level.txt
odoo12_addon_oca_custom-12.0.1.0.0.99.dev3.dist-info/RECORD
