Metadata-Version: 2.1
Name: odoo12-addon-oca-custom
Version: 12.0.1.0.0.99.dev3
Summary: Custom Settings for OCA Instance
Home-page: UNKNOWN
Author: GRAP, Akretion, Odoo Community Association (OCA)
Author-email: support@odoo-community.org
License: AGPL-3
Platform: UNKNOWN
Classifier: Programming Language :: Python
Classifier: Framework :: Odoo
Classifier: Framework :: Odoo :: 12.0
Classifier: License :: OSI Approved :: GNU Affero General Public License v3
Requires-Python: >=3.5
Requires-Dist: odoo12-addon-github-connector
Requires-Dist: odoo <12.1dev,>=12.0a
